bffacilities/__init__.py
bffacilities/__main__.py
bffacilities/_constants.py
bffacilities/_frame.py
bffacilities/_util.py
bffacilities/broadcast.py
bffacilities/gitkey.py
bffacilities/gitrepo.py
bffacilities/monitor.py
bffacilities/paperUtil.py
bffacilities/qtStatement.py
bffacilities/locale/gitrepo.pot
bffacilities/locale/monitor.pot
bffacilities/locale/en_US/LC_MESSAGES/gitrepo.mo
bffacilities/locale/en_US/LC_MESSAGES/gitrepo.po
bffacilities/locale/zh_CN/LC_MESSAGES/gitrepo.mo
bffacilities/locale/zh_CN/LC_MESSAGES/gitrepo.po
bffacilities/locale/zh_CN/LC_MESSAGES/monitor.mo
bffacilities/locale/zh_CN/LC_MESSAGES/monitor.po
brifuture_facilities-0.0.2a1.dist-info/LICENSE
brifuture_facilities-0.0.2a1.dist-info/METADATA
brifuture_facilities-0.0.2a1.dist-info/WHEEL
brifuture_facilities-0.0.2a1.dist-info/entry_points.txt
brifuture_facilities-0.0.2a1.dist-info/top_level.txt
brifuture_facilities-0.0.2a1.dist-info/RECORD
