Metadata-Version: 2.1
Name: brifuture-facilities
Version: 0.0.2a1
Summary: BriFuture's scripts set, all scripts will be written with Python3
Home-page: http://github.com/brifuture/
Author: BriFuture
Author-email: jw.brifuture@gmail.com
License: GPLv3
Keywords: facilities
Platform: UNKNOWN
Classifier: Programming Language :: Python
Classifier: Programming Language :: Python :: 3
Classifier: License :: OSI Approved :: GNU General Public License v3 (GPLv3)
Classifier: Operating System :: OS Independent
Requires-Dist: watchdog (>=0.9.0)
Requires-Dist: colorama (>=0.4.3)
